[
    {
      "name": "org.modelmapper.ModelMapper",
      "allDeclaredConstructors": true,
      "allDeclaredMethods": true,
      "allDeclaredFields": true
    },
    {
      "name": "com.dishcraft.model.DietaryRestriction",
      "allDeclaredConstructors": true,
      "allDeclaredMethods": true,
      "allDeclaredFields": true
    },
    {
      "name": "com.dishcraft.dto.DietaryRestrictionDto",
      "allDeclaredConstructors": true,
      "allDeclaredMethods": true,
      "allDeclaredFields": true
    },
    {
      "name": "com.dishcraft.model.Ingredient",
      "allDeclaredConstructors": true,
      "allDeclaredMethods": true,
      "allDeclaredFields": true
    },
    {
      "name": "com.dishcraft.dto.IngredientDto",
      "allDeclaredConstructors": true,
      "allDeclaredMethods": true,
      "allDeclaredFields": true
    },
    {
      "name": "com.dishcraft.model.RecipeIngredient",
      "allDeclaredConstructors": true,
      "allDeclaredMethods": true,
      "allDeclaredFields": true
    },
    {
      "name": "com.dishcraft.dto.RecipeIngredientDto",
      "allDeclaredConstructors": true,
      "allDeclaredMethods": true,
      "allDeclaredFields": true
    },
    {
      "name": "com.dishcraft.dto.UserResponseDto",
      "allDeclaredFields": true,
      "allDeclaredMethods": true,
      "allDeclaredConstructors": true
    },
    {
      "name": "com.dishcraft.dto.RecipeDto",
      "allDeclaredFields": true,
      "allDeclaredMethods": true,
      "allDeclaredConstructors": true
    },
    {
      "name": "com.dishcraft.dto.FeedbackDto",
      "allDeclaredFields": true,
      "allDeclaredMethods": true,
      "allDeclaredConstructors": true
    },
    {
      "name": "com.dishcraft.dto.JwtResponse",
      "allDeclaredFields": true,
      "allDeclaredMethods": true,
      "allDeclaredConstructors": true
    },
    {
      "name": "com.dishcraft.dto.LoginRequest",
      "allDeclaredFields": true,
      "allDeclaredMethods": true,
      "allDeclaredConstructors": true
    },
    {
      "name": "org.springframework.boot.http.client.ClientHttpRequestFactorySettings",
      "allDeclaredConstructors": true,
      "allDeclaredMethods": true,
      "allDeclaredFields": true,
      "methods": [
        { "name": "sslBundle", "parameterTypes": [] }
      ]
    },
    {
      "name": "org.springframework.boot.ssl.SslBundle",
      "allDeclaredConstructors": true,
      "allDeclaredMethods": true,
      "allDeclaredFields": true
    }
]
